<?xml version="1.0" encoding="UTF-8"?>
<!-- edited with XML Spy v3.5 (http://www.xmlspy.com) by Markus Nosse (University of Mass/Boston - Biology Dept.) -->
<content-description>
	<title>
		<content-item name="Common Name" method="value-only"/>
	</title>
	<sciname>
		<content-item name="Genus" method="value-only-italic"/>
		<content-item name="Species" method="value-only-italic"/>
	</sciname>
	<family>
		<content-item name="Family" method="value-only"/>
	</family>
	<images>
		<content-item name="Plant" class="id_text" method="image">
			<caption class="id_text">Plant</caption>
		</content-item>
		<content-item name="Macro" class="id_text" method="image">
			<caption class="id_text">Macro</caption>
		</content-item>
		<content-item name="Habitat" class="id_text" method="image">
			<caption class="id_text">Habitat</caption>
		</content-item>
		<content-item name="Fruit" class="id_text" method="image">
			<caption class="id_text">Fruit</caption>
		</content-item>
		<content-item name="Leaf" class="id_text" method="image">
			<caption class="id_text">Leaf</caption>
		</content-item>
		<content-item name="Stem" class="id_text" method="image">
			<caption class="id_text">Stem</caption>
		</content-item>
		<content-item name="Additional Photos" class="id_text" method="image">
			<caption class="id_text">Additional Photos</caption>
		</content-item>
	</images>
	<details>
		<content-item name="Petal Number" class="detail_text" method="plaintext">
			<caption class="detail_text">Petal Number</caption>
		</content-item>
		<content-item name="Flower Color" class="detail_text" method="plaintext">
			<caption class="detail_text">Flower Color</caption>
		</content-item>
		<content-item name="Leaf arrangement" class="detail_text" method="plaintext">
			<caption class="detail_text">Leaf arrangement</caption>
		</content-item>
		<content-item name="Leaf Shape" class="detail_text" method="plaintext">
			<caption class="detail_text">Leaf Shape</caption>
		</content-item>
		<content-item name="Growth Form" class="detail_text" method="plaintext">
			<caption class="detail_text">Growth Form</caption>
		</content-item>
		<content-item name="Degree of invasiveness on Nantucket" class="detail_text" method="plaintext">
			<caption class="detail_text">Degree of invasiveness on Nantucket</caption>
		</content-item>
		<content-item name="Degree of invasiveness in Massachusetts" class="detail_text" method="plaintext">
			<caption class="detail_text">Degree of invasiveness in Massachusetts</caption>
		</content-item>
		<content-item name="THE PLANT" class="detail_text" method="bulleted-lists">
			<caption class="detail_text">THE PLANT</caption>
		</content-item>
		<content-item name="THE LEAVES" class="detail_text" method="bulleted-lists">
			<caption class="detail_text">THE LEAVES</caption>
		</content-item>
		<content-item name="THE STEM" class="detail_text" method="bulleted-lists">
			<caption class="detail_text">THE STEM</caption>
		</content-item>
		<content-item name="THE FLOWERS" class="detail_text" method="bulleted-lists">
			<caption class="detail_text">THE FLOWERS</caption>
		</content-item>
		<content-item name="THE FRUIT" class="detail_text" method="bulleted-lists">
			<caption class="detail_text">THE FRUITS</caption>
		</content-item>
		<content-item name="THE HABITAT" class="detail_text" method="bulleted-lists">
			<caption class="detail_text">THE HABITAT</caption>
		</content-item>
		<content-item name="KEY ID FEATURES" class="detail_text" method="bulleted-lists">
			<caption class="detail_text">KEY ID FEATURES</caption>
		</content-item>
		<content-item name="NOTES" class="detail_text" method="plaintext">
			<caption class="detail_text">NOTES</caption>
		</content-item>
	</details>
	<footer>
		<content-item method="copy-of">
			<p class="credits">
				<strong>Credits: </strong>The Electronic Field Guide to the Invasive Plants of Nantucket by Cheryl Comeau Beaton, Kristen Checkalski and Jennifer Forman Orth. (c) 2005 Maria Mitchell Association.</p>
		</content-item>
	</footer>
	<tokenizers>
		<tokenizer token=";"/>
		<tokenizer token=":"/>
		<tokenizer token="("/>
	</tokenizers>
</content-description>
